{
  "/_not-found/page": "app/_not-found/page.js",
  "/account/page": "app/account/page.js",
  "/api/admin-users/route": "app/api/admin-users/route.js",
  "/api/admin/change-password/route": "app/api/admin/change-password/route.js",
  "/api/admin/logout/route": "app/api/admin/logout/route.js",
  "/api/admin/login/route": "app/api/admin/login/route.js",
  "/api/admin/me/route": "app/api/admin/me/route.js",
  "/api/admin/seed/route": "app/api/admin/seed/route.js",
  "/api/catalog/assets/[id]/route": "app/api/catalog/assets/[id]/route.js",
  "/api/admin/upload/route": "app/api/admin/upload/route.js",
  "/api/catalog/assets/route": "app/api/catalog/assets/route.js",
  "/api/catalog/categories/[id]/route": "app/api/catalog/categories/[id]/route.js",
  "/api/catalog/categories/route": "app/api/catalog/categories/route.js",
  "/api/catalog/colors/[id]/route": "app/api/catalog/colors/[id]/route.js",
  "/api/catalog/colors/route": "app/api/catalog/colors/route.js",
  "/api/catalog/home-collections/[id]/route": "app/api/catalog/home-collections/[id]/route.js",
  "/api/catalog/home-collections/route": "app/api/catalog/home-collections/route.js",
  "/api/catalog/lines/route": "app/api/catalog/lines/route.js",
  "/api/catalog/lines/[id]/route": "app/api/catalog/lines/[id]/route.js",
  "/api/catalog/products/[id]/route": "app/api/catalog/products/[id]/route.js",
  "/api/catalog/products/route": "app/api/catalog/products/route.js",
  "/api/catalog/types/route": "app/api/catalog/types/route.js",
  "/api/catalog/types/[id]/route": "app/api/catalog/types/[id]/route.js",
  "/api/payment-history/route": "app/api/payment-history/route.js",
  "/api/products/route": "app/api/products/route.js",
  "/api/products/seed/route": "app/api/products/seed/route.js",
  "/api/webhooks/midtrans/route": "app/api/webhooks/midtrans/route.js",
  "/cart/page": "app/cart/page.js",
  "/checkout/page": "app/checkout/page.js",
  "/devel/account/page": "app/devel/account/page.js",
  "/devel/cart/page": "app/devel/cart/page.js",
  "/devel/checkout/page": "app/devel/checkout/page.js",
  "/devel/order-success/page": "app/devel/order-success/page.js",
  "/favourites/page": "app/favourites/page.js",
  "/order-success/page": "app/order-success/page.js",
  "/robots.txt/route": "app/robots.txt/route.js",
  "/sitemap.xml/route": "app/sitemap.xml/route.js",
  "/api/admin/payment-gateways/route": "app/api/admin/payment-gateways/route.js",
  "/admin/page": "app/admin/page.js",
  "/devel/favourites/page": "app/devel/favourites/page.js",
  "/devel/page": "app/devel/page.js",
  "/explore/page": "app/explore/page.js",
  "/devel/product/[id]/page": "app/devel/product/[id]/page.js",
  "/page": "app/page.js",
  "/product/[id]/page": "app/product/[id]/page.js",
  "/api/checkout/route": "app/api/checkout/route.js",
  "/api/webhooks/paymenku/route": "app/api/webhooks/paymenku/route.js",
  "/api/order/[order_id]/route": "app/api/order/[order_id]/route.js",
  "/admin/dashboard/assets/page": "app/admin/dashboard/assets/page.js",
  "/admin/dashboard/categories/page": "app/admin/dashboard/categories/page.js",
  "/admin/dashboard/colors/page": "app/admin/dashboard/colors/page.js",
  "/admin/dashboard/lines/page": "app/admin/dashboard/lines/page.js",
  "/admin/dashboard/orders/page": "app/admin/dashboard/orders/page.js",
  "/admin/dashboard/payment/page": "app/admin/dashboard/payment/page.js",
  "/admin/dashboard/products/page": "app/admin/dashboard/products/page.js",
  "/admin/dashboard/settings/page": "app/admin/dashboard/settings/page.js",
  "/admin/dashboard/users/page": "app/admin/dashboard/users/page.js",
  "/admin/dashboard/page": "app/admin/dashboard/page.js",
  "/admin/dashboard/types/page": "app/admin/dashboard/types/page.js"
}